spectral_cli/__init__.py
spectral_cli/abis/Competition.json
spectral_cli/abis/CompetitionFactory.json
spectral_cli/abis/CompetitionLibrary.json
spectral_cli/abis/Consumption.json
spectral_cli/abis/DataTypes.json
spectral_cli/abis/ERC20Mock.json
spectral_cli/abis/ICompetition.json
spectral_cli/abis/ICompetitionFactory.json
spectral_cli/abis/IConsumption.json
spectral_cli/abis/IModeler.json
spectral_cli/abis/IServiceAgreement.json
spectral_cli/abis/Modeler.json
spectral_cli/abis/ModelerLibrary.json
spectral_cli/abis/NewCompetition.json
spectral_cli/abis/NewModeler.json
spectral_cli/abis/ProxyBeaconDeployer.json
spectral_cli/abis/ServiceAgreement.json
spectral_cli/abis/SpectralToken.json
spectral_cli/abis/WalletFactory.json
spectral_cli/abis/WalletSimple.json
spectral_cli/abis/__init__.py
spectral_cli/abis/abis.py
spectral_cli/abis/process_json_files.sh
spectral_cli/config_manager.py
spectral_cli/ezkl_wrapper/__init__.py
spectral_cli/ezkl_wrapper/ezkl_wrapper.py
spectral_cli/prod_constants.py
spectral_cli/spectralaisdk.py
spectral_cli-0.1.20.dist-info/LICENSE
spectral_cli-0.1.20.dist-info/METADATA
spectral_cli-0.1.20.dist-info/WHEEL
spectral_cli-0.1.20.dist-info/entry_points.txt
spectral_cli-0.1.20.dist-info/RECORD
