Metadata-Version: 2.1
Name: spectral-cli
Version: 0.1.20
Summary: Spectral CLI allows you to participate in challenges on the Spectral Finance Platform.
Keywords: machine learning,ai,data science,web3
Author: Spectral Finance
Author-email: maciej@spectral.finance
Requires-Python: >=3.11.6,<4
Classifier: License :: OSI Approved :: MIT License
Classifier: Programming Language :: Python :: 3
Classifier: Programming Language :: Python :: 3.12
Classifier: Programming Language :: Python :: 3.10
Classifier: Programming Language :: Python :: 3.11
Classifier: Programming Language :: Python :: 3.7
Classifier: Programming Language :: Python :: 3.8
Classifier: Programming Language :: Python :: 3.9
Requires-Dist: click (>=8.1.7,<9.0.0)
Requires-Dist: ezkl (==3.9.3)
Requires-Dist: pandas (>=2.1.4,<3.0.0)
Requires-Dist: pyarrow (>=14.0.2,<15.0.0)
Requires-Dist: requests (>=2.31.0)
Requires-Dist: retrying (>=1.3.4,<2.0.0)
Requires-Dist: tqdm (>=4.66.1,<5.0.0)
Requires-Dist: web3 (>=6.11.1)
Project-URL: Repository, https://github.com/Spectral-Finance/spectral-ai-sdk
